wechatsogou/__init__.py
wechatsogou/api.py
wechatsogou/const.py
wechatsogou/exceptions.py
wechatsogou/filecache.py
wechatsogou/five.py
wechatsogou/identify_image.py
wechatsogou/request.py
wechatsogou/structuring.py
wechatsogou/tools.py
wechatsogou-4.5.4.dist-info/DESCRIPTION.rst
wechatsogou-4.5.4.dist-info/METADATA
wechatsogou-4.5.4.dist-info/RECORD
wechatsogou-4.5.4.dist-info/WHEEL
wechatsogou-4.5.4.dist-info/metadata.json
wechatsogou-4.5.4.dist-info/top_level.txt
