Metadata-Version: 2.0
Name: wechatsogou
Version: 4.5.4
Summary: Api for wechat mp with sogou
Home-page: https://github.com/Chyroc/WechatSogou
Author: Chyroc
Author-email: chen_yunpeng@foxmail.com
License: MIT License
Platform: UNKNOWN
Classifier: Intended Audience :: Developers
Classifier: License :: OSI Approved :: MIT License
Classifier: Operating System :: MacOS :: MacOS X
Classifier: Operating System :: Microsoft :: Windows
Classifier: Operating System :: POSIX
Classifier: Programming Language :: Python
Classifier: Programming Language :: Python :: 2.7
Classifier: Programming Language :: Python :: 3.5
Classifier: Programming Language :: Python :: 3.6
Classifier: Topic :: Software Development :: Libraries :: Python Modules
Classifier: Programming Language :: Python :: Implementation :: PyPy
Classifier: Programming Language :: Python :: Implementation :: CPython
Requires-Dist: Pillow
Requires-Dist: Werkzeug
Requires-Dist: bs4
Requires-Dist: future
Requires-Dist: lxml
Requires-Dist: requests
Requires-Dist: six
Requires-Dist: xlrd
